qspypy/__init__.py
qspypy/config.py
qspypy/fixtures.py
qspypy/qspy.py
qspypy/qutest.py
qspypy/qutest_convert.py
qspypy-1.1.0.dist-info/METADATA
qspypy-1.1.0.dist-info/RECORD
qspypy-1.1.0.dist-info/WHEEL
qspypy-1.1.0.dist-info/entry_points.txt
qspypy-1.1.0.dist-info/top_level.txt
tests/config.py
tests/conftest.py
tests/test_philo.py
tests/test_qspy.py
tests/test_table.py
