Metadata-Version: 2.1
Name: qspypy
Version: 1.1.0
Summary: Python implementation of qspy Tcl scripts
Home-page: https://github.com/LotusEngineering/qpboost/tree/master/qspypy
Author: Lotus Engineering, LLC
Author-email: dominic_valentino@lotusengineeringllc.com
License: UNKNOWN
Keywords: qp qpcpp qtools qpc qutest
Platform: UNKNOWN
Classifier: Programming Language :: Python :: 3
Classifier: License :: OSI Approved :: MIT License
Classifier: Operating System :: OS Independent
Requires-Dist: pytest (>=3.6.1)
